DM23004UNO/__init__.py
DM23004UNO/iterativos.py
DM23004UNO/lineal.py
DM23004UNO/no_lineal.py
dm23004uno-0.3.dist-info/licenses/LICENSE
dm23004uno-0.3.dist-info/METADATA
dm23004uno-0.3.dist-info/WHEEL
dm23004uno-0.3.dist-info/top_level.txt
dm23004uno-0.3.dist-info/RECORD
